noteseries/__init__.py
noteseries/experiment/__init__.py
noteseries/experiment/prime/__init__.py
noteseries/experiment/prime/core.py
noteseries-0.0.16.dist-info/METADATA
noteseries-0.0.16.dist-info/WHEEL
noteseries-0.0.16.dist-info/top_level.txt
noteseries-0.0.16.dist-info/RECORD
