Metadata-Version: 2.1
Name: noteseries
Version: 0.0.16
Summary: noteseries
Home-page: https://github.com/1007530194
Author: niuliangtao
Author-email: 1007530194@qq.com
License: UNKNOWN
Platform: UNKNOWN
Requires-Dist: notebuild
Requires-Dist: sqlalchemy
